poetry_version/__init__.py
poetry_version-0.2.0.dist-info/LICENSE
poetry_version-0.2.0.dist-info/WHEEL
poetry_version-0.2.0.dist-info/METADATA
poetry_version-0.2.0.dist-info/RECORD
