Metadata-Version: 2.1
Name: poetry-version
Version: 0.2.0
Summary: Python library for extracting version from poetry pyproject.toml file (deprecated)
Home-page: https://github.com/rominf/poetry-version
License: Apache-2.0
Keywords: poetry,version
Author: Roman Inflianskas
Author-email: infroma@gmail.com
Requires-Python: >=2.7, !=3.0.*, !=3.1.*, !=3.2.*, !=3.3.*
Classifier: Development Status :: 7 - Inactive
Classifier: License :: OSI Approved :: Apache Software License
Classifier: Programming Language :: Python :: 2
Classifier: Programming Language :: Python :: 2.7
Classifier: Programming Language :: Python :: 3
Classifier: Programming Language :: Python :: 3.10
Classifier: Programming Language :: Python :: 3.4
Classifier: Programming Language :: Python :: 3.5
Classifier: Programming Language :: Python :: 3.6
Classifier: Programming Language :: Python :: 3.7
Classifier: Programming Language :: Python :: 3.8
Classifier: Programming Language :: Python :: 3.9
Classifier: Topic :: Software Development :: Build Tools
Classifier: Topic :: Software Development :: Libraries :: Python Modules
Requires-Dist: tomlkit (>=0.4.6,<0.6.0)
Project-URL: Repository, https://github.com/rominf/poetry-version
